{"categories":["all","heard","year-2025","programming-problem"],"posts":{"mn":[{"title":"The hanselminutes podcast - temporal","author":"Төгөлдөр","createdAt":"2025-07-14T02:24:41.054Z","updatedAt":"2025-07-14T02:24:41.054Z","categories":["heard","year-2025","all"],"slug":"/heard/2025-07-14-temporal-heard","language":"mn","id":1,"startText":"[**Hanselminutes**](https://www.youtube.com/playlist?list=PL0M0zPgJ3HSf55bZCgrRfsYTApHzBhzMi) подкастын зочноор Temporal ийн ахлах инженер _**Preeti Somal**_ оролцлоо . Бид юу сонссоноо хуваалцах болно . Мөн шинээр сурсан англи хэллэгээ хуваалцана ."},{"title":"Хувьцаа аваад зараад яаж хамгийн их ашиг олох вэ ?","author":"Төгөлдөр","createdAt":"2025-07-11T11:30:36.287Z","updatedAt":"2025-07-11T11:30:36.287Z","categories":["programming-problem","year-2025","all"],"slug":"/programming/2025-07-11-stock-buy-and-sell","language":"mn","id":0,"startText":"Бид энэхүү блогоор 🌳🌳 амазоны 🌳🌳 ярилцлаганд ирдэг бодлогыг бодох болно"}],"en":[{"title":"The hanselminutes podcast - temporal","author":"Tuguldur","createdAt":"2025-07-14T02:24:41.054Z","updatedAt":"2025-07-14T02:24:41.054Z","categories":["heard","year-2025","all"],"slug":"/heard/2025-07-14-temporal-heard","language":"en","id":3,"startText":"I am wondering what tech leaders talk ..."},{"title":"How to get the maximum profit by buying and selling stocks?","author":"Tuguldur","createdAt":"2025-07-11T11:30:36.287Z","updatedAt":"2025-07-11T11:30:36.287Z","categories":["programming-problem","year-2025","all"],"slug":"/programming/2025-07-11-stock-buy-and-sell","language":"en","id":2,"startText":"In this blog, we will solve a problem that comes up in 🌳🌳 Amazon 🌳🌳 interviews."}]}}